CHANGES.rst
LICENSE.txt
MANIFEST.in
README.rst
TODO.txt
master.cfg.sample
setup.cfg
setup.py
slaves.cfg.sample
anybox/__init__.py
anybox.buildbot.openerp.egg-info/PKG-INFO
anybox.buildbot.openerp.egg-info/SOURCES.txt
anybox.buildbot.openerp.egg-info/dependency_links.txt
anybox.buildbot.openerp.egg-info/entry_points.txt
anybox.buildbot.openerp.egg-info/namespace_packages.txt
anybox.buildbot.openerp.egg-info/not-zip-safe
anybox.buildbot.openerp.egg-info/requires.txt
anybox.buildbot.openerp.egg-info/top_level.txt
anybox/buildbot/__init__.py
anybox/buildbot/openerp/__init__.py
anybox/buildbot/openerp/buildouts.py
anybox/buildbot/openerp/bzr_buildbot.py
anybox/buildbot/openerp/capability.py
anybox/buildbot/openerp/configurator.py
anybox/buildbot/openerp/constants.py
anybox/buildbot/openerp/scheduler.py
anybox/buildbot/openerp/steps.py
anybox/buildbot/openerp/utils.py
anybox/buildbot/openerp/version.py
anybox/buildbot/openerp/watch.py
anybox/buildbot/openerp/build_utils/analyze_oerp_tests.py
anybox/buildbot/openerp/build_utils/buildout_bzr_dl.py
anybox/buildbot/openerp/build_utils/buildout_git_dl.py
anybox/buildbot/openerp/build_utils/buildout_hg_dl.py
anybox/buildbot/openerp/build_utils/port_reserve.py
anybox/buildbot/openerp/subfactories/__init__.py
anybox/buildbot/openerp/subfactories/db.py
anybox/buildbot/openerp/subfactories/download.py
anybox/buildbot/openerp/subfactories/postbuildout.py
anybox/buildbot/openerp/subfactories/postdownload.py
anybox/buildbot/openerp/tests/__init__.py
anybox/buildbot/openerp/tests/base.py
anybox/buildbot/openerp/tests/test_builders.py
anybox/buildbot/openerp/tests/test_pollers.py
anybox/buildbot/openerp/tests/test_schedulers.py
anybox/buildbot/openerp/tests/test_slaves.py
anybox/buildbot/openerp/tests/test_watch.py
buildouts/6.0-anybox.cfg
buildouts/6.1.cfg
buildouts/7.0.cfg
buildouts/MANIFEST.cfg
buildouts/ocb-7.0.cfg
buildouts/trunk.cfg