Metadata-Version: 1.1
Name: anybox.buildbot.openerp
Version: 0.9
Summary: Buildbot setup for buildout based openerp installations
Home-page: http://pypi.python.org/pypi/anybox.buildbot.openerp
Author: Anybox SAS
Author-email: gracinet@anybox.fr
License: Affero GPLv3
Platform: UNKNOWN
Classifier: Intended Audience :: Developers
Classifier: Intended Audience :: System Administrators
Classifier: Topic :: Software Development :: Build Tools
Classifier: Topic :: Software Development :: Testing
Classifier: Topic :: Software Development :: Quality Assurance
Classifier: Topic :: Software Development :: Libraries :: Python Modules
Classifier: License :: OSI Approved :: GNU Affero General Public License v3 or later (AGPLv3+)
